<?xml version="1.0" encoding="UTF-8"?>
<objects serializationModel="Studio.02.03.00">
	<object class="AudioFile" id="{ad2efeaa-2896-4832-bd70-aaab23800dc4}">
		<property name="assetPath">
			<value>Ambience/City/ambience_city_walla_chatter_6.ogg</value>
		</property>
		<property name="frequencyInKHz">
			<value>48</value>
		</property>
		<property name="channelCount">
			<value>1</value>
		</property>
		<property name="length">
			<value>0.68110416666666662</value>
		</property>
		<relationship name="masterAssetFolder">
			<destination>{92eea667-545b-4b81-bb7c-789160095b4b}</destination>
		</relationship>
	</object>
</objects>
